ollama_rag/__init__.py
ollama_rag/configs.py
ollama_rag/data_loader.py
ollama_rag/document_tracker.py
ollama_rag/indexer.py
ollama_rag/models.py
ollama_rag/ollama_rag.py
ollama_rag/prompts.py
ollama_rag/query_engine.py
ollama_rag-0.4.1.dist-info/METADATA
ollama_rag-0.4.1.dist-info/WHEEL
ollama_rag-0.4.1.dist-info/top_level.txt
ollama_rag-0.4.1.dist-info/RECORD
