Metadata-Version: 2.1
Name: ollama_rag
Version: 0.4.1
Summary: A RAG (Retrieval-Augmented Generation) system using Llama Index and ChromaDB
Home-page: https://github.com/Zakk-Yang/ollama-rag.git
Author: Zakk Yang
Author-email: zakkyang@protonmail.com
Classifier: Programming Language :: Python :: 3
Classifier: License :: OSI Approved :: MIT License
Classifier: Operating System :: OS Independent
Requires-Python: >=3.7
Requires-Dist: llama-index
Requires-Dist: llama-index-llms-ollama
Requires-Dist: llama-index-embeddings-huggingface
Requires-Dist: chromadb
Requires-Dist: llama-index-vector-stores-chroma
Requires-Dist: pandas
